trendhunter/__init__.py
trendhunter/api.py
trendhunter/formatters.py
trendhunter/taxonomies.py
trendhunter/tuples.py
trendhunter/utils.py
trendhunter/bin/__init__.py
trendhunter/bin/console.py
trendhunter-1.0.0.dist-info/LICENSE
trendhunter-1.0.0.dist-info/METADATA
trendhunter-1.0.0.dist-info/WHEEL
trendhunter-1.0.0.dist-info/entry_points.txt
trendhunter-1.0.0.dist-info/top_level.txt
trendhunter-1.0.0.dist-info/RECORD
